{
  "id": "8bb54c6e-75b3-4ab8-97e3-dbc9617daeca",
  "prevId": "1c2aca79-2355-4f86-a028-075ba5fa37a3",
  "version": "7",
  "dialect": "postgresql",
  "tables": {
    "public.concerts": {
      "name": "concerts",
      "schema": "",
      "columns": {
        "id": {
          "name": "id",
          "type": "uuid",
          "primaryKey": true,
          "notNull": true,
          "default": "gen_random_uuid()"
        },
        "name": {
          "name": "name",
          "type": "varchar(255)",
          "primaryKey": false,
          "notNull": true
        },
        "description": {
          "name": "description",
          "type": "text",
          "primaryKey": false,
          "notNull": false
        },
        "venue": {
          "name": "venue",
          "type": "varchar(255)",
          "primaryKey": false,
          "notNull": true
        },
        "artist_name": {
          "name": "artist_name",
          "type": "varchar(255)",
          "primaryKey": false,
          "notNull": true
        },
        "event_date": {
          "name": "event_date",
          "type": "timestamp with time zone",
          "primaryKey": false,
          "notNull": true
        },
        "status": {
          "name": "status",
          "type": "concert_status",
          "typeSchema": "public",
          "primaryKey": false,
          "notNull": true,
          "default": "'draft'"
        },
        "created_at": {
          "name": "created_at",
          "type": "timestamp with time zone",
          "primaryKey": false,
          "notNull": true,
          "default": "now()"
        },
        "updated_at": {
          "name": "updated_at",
          "type": "timestamp with time zone",
          "primaryKey": false,
          "notNull": true,
          "default": "now()"
        }
      },
      "indexes": {},
      "foreignKeys": {},
      "compositePrimaryKeys": {},
      "uniqueConstraints": {},
      "policies": {},
      "checkConstraints": {},
      "isRLSEnabled": false
    },
    "public.ticket_tiers": {
      "name": "ticket_tiers",
      "schema": "",
      "columns": {
        "id": {
          "name": "id",
          "type": "uuid",
          "primaryKey": true,
          "notNull": true,
          "default": "gen_random_uuid()"
        },
        "concert_id": {
          "name": "concert_id",
          "type": "uuid",
          "primaryKey": false,
          "notNull": true
        },
        "name": {
          "name": "name",
          "type": "varchar(100)",
          "primaryKey": false,
          "notNull": true
        },
        "price": {
          "name": "price",
          "type": "numeric(12, 2)",
          "primaryKey": false,
          "notNull": true
        },
        "total_qty": {
          "name": "total_qty",
          "type": "integer",
          "primaryKey": false,
          "notNull": true
        },
        "reserved_qty": {
          "name": "reserved_qty",
          "type": "integer",
          "primaryKey": false,
          "notNull": true,
          "default": 0
        },
        "created_at": {
          "name": "created_at",
          "type": "timestamp with time zone",
          "primaryKey": false,
          "notNull": true,
          "default": "now()"
        },
        "updated_at": {
          "name": "updated_at",
          "type": "timestamp with time zone",
          "primaryKey": false,
          "notNull": true,
          "default": "now()"
        }
      },
      "indexes": {},
      "foreignKeys": {
        "ticket_tiers_concert_id_concerts_id_fk": {
          "name": "ticket_tiers_concert_id_concerts_id_fk",
          "tableFrom": "ticket_tiers",
          "tableTo": "concerts",
          "columnsFrom": [
            "concert_id"
          ],
          "columnsTo": [
            "id"
          ],
          "onDelete": "cascade",
          "onUpdate": "no action"
        }
      },
      "compositePrimaryKeys": {},
      "uniqueConstraints": {},
      "policies": {},
      "checkConstraints": {},
      "isRLSEnabled": false
    },
    "public.voucher_campaigns": {
      "name": "voucher_campaigns",
      "schema": "",
      "columns": {
        "id": {
          "name": "id",
          "type": "uuid",
          "primaryKey": true,
          "notNull": true,
          "default": "gen_random_uuid()"
        },
        "name": {
          "name": "name",
          "type": "varchar(255)",
          "primaryKey": false,
          "notNull": true
        },
        "code": {
          "name": "code",
          "type": "varchar(50)",
          "primaryKey": false,
          "notNull": true
        },
        "discount_type": {
          "name": "discount_type",
          "type": "discount_type",
          "typeSchema": "public",
          "primaryKey": false,
          "notNull": true
        },
        "discount_value": {
          "name": "discount_value",
          "type": "numeric(10, 2)",
          "primaryKey": false,
          "notNull": true
        },
        "max_uses": {
          "name": "max_uses",
          "type": "integer",
          "primaryKey": false,
          "notNull": true
        },
        "used_count": {
          "name": "used_count",
          "type": "integer",
          "primaryKey": false,
          "notNull": true,
          "default": 0
        },
        "min_order_value": {
          "name": "min_order_value",
          "type": "numeric(12, 2)",
          "primaryKey": false,
          "notNull": false,
          "default": "'0'"
        },
        "expires_at": {
          "name": "expires_at",
          "type": "timestamp with time zone",
          "primaryKey": false,
          "notNull": false
        },
        "concert_id": {
          "name": "concert_id",
          "type": "uuid",
          "primaryKey": false,
          "notNull": false
        },
        "created_at": {
          "name": "created_at",
          "type": "timestamp with time zone",
          "primaryKey": false,
          "notNull": true,
          "default": "now()"
        }
      },
      "indexes": {},
      "foreignKeys": {
        "voucher_campaigns_concert_id_concerts_id_fk": {
          "name": "voucher_campaigns_concert_id_concerts_id_fk",
          "tableFrom": "voucher_campaigns",
          "tableTo": "concerts",
          "columnsFrom": [
            "concert_id"
          ],
          "columnsTo": [
            "id"
          ],
          "onDelete": "no action",
          "onUpdate": "no action"
        }
      },
      "compositePrimaryKeys": {},
      "uniqueConstraints": {
        "voucher_campaigns_code_unique": {
          "name": "voucher_campaigns_code_unique",
          "nullsNotDistinct": false,
          "columns": [
            "code"
          ]
        }
      },
      "policies": {},
      "checkConstraints": {},
      "isRLSEnabled": false
    },
    "public.bookings": {
      "name": "bookings",
      "schema": "",
      "columns": {
        "id": {
          "name": "id",
          "type": "uuid",
          "primaryKey": true,
          "notNull": true,
          "default": "gen_random_uuid()"
        },
        "user_id": {
          "name": "user_id",
          "type": "varchar(255)",
          "primaryKey": false,
          "notNull": true
        },
        "ticket_tier_id": {
          "name": "ticket_tier_id",
          "type": "uuid",
          "primaryKey": false,
          "notNull": true
        },
        "concert_id": {
          "name": "concert_id",
          "type": "uuid",
          "primaryKey": false,
          "notNull": true
        },
        "quantity": {
          "name": "quantity",
          "type": "integer",
          "primaryKey": false,
          "notNull": true,
          "default": 1
        },
        "unit_price": {
          "name": "unit_price",
          "type": "numeric(12, 2)",
          "primaryKey": false,
          "notNull": true
        },
        "total_amount": {
          "name": "total_amount",
          "type": "numeric(12, 2)",
          "primaryKey": false,
          "notNull": true
        },
        "discount_amount": {
          "name": "discount_amount",
          "type": "numeric(12, 2)",
          "primaryKey": false,
          "notNull": true,
          "default": "'0'"
        },
        "final_amount": {
          "name": "final_amount",
          "type": "numeric(12, 2)",
          "primaryKey": false,
          "notNull": true
        },
        "voucher_code": {
          "name": "voucher_code",
          "type": "varchar(50)",
          "primaryKey": false,
          "notNull": false
        },
        "status": {
          "name": "status",
          "type": "booking_status",
          "typeSchema": "public",
          "primaryKey": false,
          "notNull": true,
          "default": "'pending'"
        },
        "idempotency_key": {
          "name": "idempotency_key",
          "type": "varchar(255)",
          "primaryKey": false,
          "notNull": false
        },
        "is_flagged": {
          "name": "is_flagged",
          "type": "integer",
          "primaryKey": false,
          "notNull": true,
          "default": 0
        },
        "flag_reason": {
          "name": "flag_reason",
          "type": "text",
          "primaryKey": false,
          "notNull": false
        },
        "created_at": {
          "name": "created_at",
          "type": "timestamp with time zone",
          "primaryKey": false,
          "notNull": true,
          "default": "now()"
        },
        "updated_at": {
          "name": "updated_at",
          "type": "timestamp with time zone",
          "primaryKey": false,
          "notNull": true,
          "default": "now()"
        }
      },
      "indexes": {},
      "foreignKeys": {
        "bookings_ticket_tier_id_ticket_tiers_id_fk": {
          "name": "bookings_ticket_tier_id_ticket_tiers_id_fk",
          "tableFrom": "bookings",
          "tableTo": "ticket_tiers",
          "columnsFrom": [
            "ticket_tier_id"
          ],
          "columnsTo": [
            "id"
          ],
          "onDelete": "no action",
          "onUpdate": "no action"
        },
        "bookings_concert_id_concerts_id_fk": {
          "name": "bookings_concert_id_concerts_id_fk",
          "tableFrom": "bookings",
          "tableTo": "concerts",
          "columnsFrom": [
            "concert_id"
          ],
          "columnsTo": [
            "id"
          ],
          "onDelete": "no action",
          "onUpdate": "no action"
        }
      },
      "compositePrimaryKeys": {},
      "uniqueConstraints": {
        "bookings_idempotency_key_unique": {
          "name": "bookings_idempotency_key_unique",
          "nullsNotDistinct": false,
          "columns": [
            "idempotency_key"
          ]
        }
      },
      "policies": {},
      "checkConstraints": {},
      "isRLSEnabled": false
    },
    "public.users": {
      "name": "users",
      "schema": "",
      "columns": {
        "id": {
          "name": "id",
          "type": "uuid",
          "primaryKey": true,
          "notNull": true,
          "default": "gen_random_uuid()"
        },
        "email": {
          "name": "email",
          "type": "varchar(255)",
          "primaryKey": false,
          "notNull": true
        },
        "password_hash": {
          "name": "password_hash",
          "type": "varchar(255)",
          "primaryKey": false,
          "notNull": true
        },
        "name": {
          "name": "name",
          "type": "varchar(255)",
          "primaryKey": false,
          "notNull": true
        },
        "role": {
          "name": "role",
          "type": "user_role",
          "typeSchema": "public",
          "primaryKey": false,
          "notNull": true,
          "default": "'customer'"
        },
        "created_at": {
          "name": "created_at",
          "type": "timestamp with time zone",
          "primaryKey": false,
          "notNull": true,
          "default": "now()"
        },
        "updated_at": {
          "name": "updated_at",
          "type": "timestamp with time zone",
          "primaryKey": false,
          "notNull": true,
          "default": "now()"
        }
      },
      "indexes": {},
      "foreignKeys": {},
      "compositePrimaryKeys": {},
      "uniqueConstraints": {
        "users_email_unique": {
          "name": "users_email_unique",
          "nullsNotDistinct": false,
          "columns": [
            "email"
          ]
        }
      },
      "policies": {},
      "checkConstraints": {},
      "isRLSEnabled": false
    }
  },
  "enums": {
    "public.concert_status": {
      "name": "concert_status",
      "schema": "public",
      "values": [
        "draft",
        "on_sale",
        "sold_out",
        "cancelled",
        "completed"
      ]
    },
    "public.discount_type": {
      "name": "discount_type",
      "schema": "public",
      "values": [
        "percentage",
        "fixed"
      ]
    },
    "public.booking_status": {
      "name": "booking_status",
      "schema": "public",
      "values": [
        "pending",
        "confirmed",
        "cancelled",
        "failed"
      ]
    },
    "public.user_role": {
      "name": "user_role",
      "schema": "public",
      "values": [
        "customer",
        "admin"
      ]
    }
  },
  "schemas": {},
  "sequences": {},
  "roles": {},
  "policies": {},
  "views": {},
  "_meta": {
    "columns": {},
    "schemas": {},
    "tables": {}
  }
}